mongobackuptools/__init__.py
mongobackuptools/backups.py
mongobackuptools/s3.py
mongobackuptools/shell.py
mongobackuptools-0.7.dist-info/LICENSE
mongobackuptools-0.7.dist-info/METADATA
mongobackuptools-0.7.dist-info/WHEEL
mongobackuptools-0.7.dist-info/top_level.txt
mongobackuptools-0.7.dist-info/RECORD
